_libc.py
setup.py
micropython_libc.egg-info/PKG-INFO
micropython_libc.egg-info/SOURCES.txt
micropython_libc.egg-info/dependency_links.txt
micropython_libc.egg-info/top_level.txt