Metadata-Version: 1.0
Name: micropython-libc
Version: 0.3
Summary: MicroPython FFI helper module (deprecated)
Home-page: https://github.com/micropython/micropython/issues/405
Author: MicroPython Developers
Author-email: micro-python@googlegroups.com
License: MIT
Platform: UNKNOWN
